unav/__init__.py
unav/server.py
unav/visualization_gui.py
unav/conversation/__init__.py
unav/conversation/server.cpython-38-x86_64-linux-gnu.so
unav/conversation/utils/__init__.py
unav/conversation/utils/messaging.py
unav/conversation/utils/utils.py
unav/feature/__init__.py
unav/feature/global_extractor.cpython-38-x86_64-linux-gnu.so
unav/feature/local_extractor.cpython-38-x86_64-linux-gnu.so
unav/feature/local_matcher.cpython-38-x86_64-linux-gnu.so
unav/loader/__init__.py
unav/loader/data_loader.cpython-38-x86_64-linux-gnu.so
unav/loader/downloader.cpython-38-x86_64-linux-gnu.so
unav/navigation/__init__.py
unav/navigation/command.cpython-38-x86_64-linux-gnu.so
unav/navigation/trajectory.cpython-38-x86_64-linux-gnu.so
unav/third_party/__init__.py
unav/third_party/global_feature/__init__.py
unav/third_party/global_feature/mixVPR_main/__init__.py
unav/third_party/global_feature/mixVPR_main/demo.py
unav/third_party/global_feature/mixVPR_main/main.py
unav/third_party/global_feature/mixVPR_main/models/__init__.py
unav/third_party/global_feature/mixVPR_main/models/helper.py
unav/third_party/global_feature/mixVPR_main/models/aggregators/__init__.py
unav/third_party/global_feature/mixVPR_main/models/aggregators/convap.py
unav/third_party/global_feature/mixVPR_main/models/aggregators/cosplace.py
unav/third_party/global_feature/mixVPR_main/models/aggregators/gem.py
unav/third_party/global_feature/mixVPR_main/models/aggregators/mixvpr.py
unav/third_party/global_feature/mixVPR_main/models/backbones/__init__.py
unav/third_party/global_feature/mixVPR_main/models/backbones/efficientnet.py
unav/third_party/global_feature/mixVPR_main/models/backbones/resnet.py
unav/third_party/global_feature/mixVPR_main/models/backbones/swin.py
unav/third_party/global_feature/mixVPR_main/utils/__init__.py
unav/third_party/global_feature/mixVPR_main/utils/losses.py
unav/third_party/global_feature/mixVPR_main/utils/validation.py
unav/third_party/global_feature/pytorch_NetVlad/Feature_Extractor.py
unav-0.1.40.dist-info/METADATA
unav-0.1.40.dist-info/WHEEL
unav-0.1.40.dist-info/top_level.txt
unav-0.1.40.dist-info/RECORD
