Metadata-Version: 2.1
Name: unav
Version: 0.1.40
Summary: UNav is designed for helping navigation of visually impaired people
Home-page: https://github.com/yourusername/UNav
Author: Your Name
Author-email: your.email@example.com
Classifier: Development Status :: 4 - Beta
Classifier: Intended Audience :: Education
Classifier: Intended Audience :: Science/Research
Classifier: Topic :: Scientific/Engineering :: Artificial Intelligence
Classifier: License :: OSI Approved :: MIT License
Classifier: Programming Language :: Python :: 3.6
Classifier: Programming Language :: Python :: 3.7
Classifier: Programming Language :: Python :: 3.8
Classifier: Programming Language :: Python :: 3.9
Classifier: Programming Language :: Python :: 3.10
Requires-Python: >=3.6
Requires-Dist: numpy
Requires-Dist: torchvision
Requires-Dist: einops
Requires-Dist: pytorch-metric-learning
Requires-Dist: faiss-gpu
Requires-Dist: prettytable
Requires-Dist: timm
Requires-Dist: opencv-python
Requires-Dist: h5py
Requires-Dist: scikit-image
